[
  {
    "id": 1765457526704,
    "tipo": "pedido",
    "idLibro": 1765457472705,
    "libroNombre": "Matematica 1",
    "mailVendedor": "bg1373@est.ort.edu.ar",
    "nombreVendedor": "Juan",
    "mailComprador": "rome@gmail.com",
    "nombreComprador": "romero",
    "estado": "aceptado",
    "fecha": "2025-12-11T12:52:06.705Z"
  },
  {
    "id": 1765457578544,
    "tipo": "pedido",
    "idLibro": 1765457472705,
    "libroNombre": "Matematica 1",
    "mailVendedor": "bg1373@est.ort.edu.ar",
    "nombreVendedor": "Juan",
    "mailComprador": "rome@gmail.com",
    "nombreComprador": "romero",
    "estado": "aceptado",
    "fecha": "2025-12-11T12:52:58.544Z"
  },
  {
    "id": 1765457888480,
    "tipo": "pedido",
    "idLibro": 1765457472705,
    "libroNombre": "Matematica 1",
    "mailVendedor": "bg1373@est.ort.edu.ar",
    "nombreVendedor": "Juan",
    "mailComprador": "rome@gmail.com",
    "nombreComprador": "romero",
    "estado": "rechazado",
    "fecha": "2025-12-11T12:58:08.480Z"
  },
  {
    "id": 1765458137291,
    "tipo": "pedido",
    "idLibro": 1765458104315,
    "libroNombre": "Matematica 1",
    "mailVendedor": "bg1373@est.ort.edu.ar",
    "nombreVendedor": "Juan",
    "mailComprador": "rome@gmail.com",
    "nombreComprador": "romero",
    "estado": "aceptado",
    "fecha": "2025-12-11T13:02:17.291Z"
  },
  {
    "id": 1765458176474,
    "tipo": "respuesta",
    "idLibro": 1765458104315,
    "libroNombre": "Matematica 1",
    "mailVendedor": "bg1373@est.ort.edu.ar",
    "nombreVendedor": "Juan",
    "mailComprador": "rome@gmail.com",
    "nombreComprador": "romero",
    "estado": "aceptado",
    "mensaje": "Tu pedido del libro \"Matematica 1\" fue aceptado por Juan",
    "fecha": "2025-12-11T13:02:56.474Z"
  },
  {
    "id": 1765458190382,
    "tipo": "respuesta",
    "idLibro": 1765457472705,
    "libroNombre": "Matematica 1",
    "mailVendedor": "bg1373@est.ort.edu.ar",
    "nombreVendedor": "Juan",
    "mailComprador": "rome@gmail.com",
    "nombreComprador": "romero",
    "estado": "rechazado",
    "mensaje": "Tu pedido del libro \"Matematica 1\" fue rechazado por Juan",
    "fecha": "2025-12-11T13:03:10.381Z"
  },
  {
    "id": 1765458198237,
    "tipo": "respuesta",
    "idLibro": 1765457472705,
    "libroNombre": "Matematica 1",
    "mailVendedor": "bg1373@est.ort.edu.ar",
    "nombreVendedor": "Juan",
    "mailComprador": "rome@gmail.com",
    "nombreComprador": "romero",
    "estado": "aceptado",
    "mensaje": "Tu pedido del libro \"Matematica 1\" fue aceptado por Juan",
    "fecha": "2025-12-11T13:03:18.237Z"
  },
  {
    "id": 1765458203604,
    "tipo": "respuesta",
    "idLibro": 1765457472705,
    "libroNombre": "Matematica 1",
    "mailVendedor": "bg1373@est.ort.edu.ar",
    "nombreVendedor": "Juan",
    "mailComprador": "rome@gmail.com",
    "nombreComprador": "romero",
    "estado": "aceptado",
    "mensaje": "Tu pedido del libro \"Matematica 1\" fue aceptado por Juan",
    "fecha": "2025-12-11T13:03:23.604Z"
  }
]